odoo/addons/base_user_role_company/README.rst
odoo/addons/base_user_role_company/__init__.py
odoo/addons/base_user_role_company/__manifest__.py
odoo/addons/base_user_role_company/controllers/__init__.py
odoo/addons/base_user_role_company/controllers/main.py
odoo/addons/base_user_role_company/i18n/base_user_role_company.pot
odoo/addons/base_user_role_company/i18n/es.po
odoo/addons/base_user_role_company/i18n/it.po
odoo/addons/base_user_role_company/i18n/pt.po
odoo/addons/base_user_role_company/models/__init__.py
odoo/addons/base_user_role_company/models/ir_http.py
odoo/addons/base_user_role_company/models/role.py
odoo/addons/base_user_role_company/models/user.py
odoo/addons/base_user_role_company/readme/CONFIGURE.md
odoo/addons/base_user_role_company/readme/CONTRIBUTORS.md
odoo/addons/base_user_role_company/readme/DESCRIPTION.md
odoo/addons/base_user_role_company/readme/USAGE.md
odoo/addons/base_user_role_company/static/description/icon.png
odoo/addons/base_user_role_company/static/description/index.html
odoo/addons/base_user_role_company/tests/__init__.py
odoo/addons/base_user_role_company/tests/test_role_per_company.py
odoo/addons/base_user_role_company/tests/test_use_only_enabled_roles.py
odoo/addons/base_user_role_company/views/role.xml
odoo/addons/base_user_role_company/views/user.xml
odoo_addon_base_user_role_company-18.0.1.0.2.dist-info/METADATA
odoo_addon_base_user_role_company-18.0.1.0.2.dist-info/WHEEL
odoo_addon_base_user_role_company-18.0.1.0.2.dist-info/top_level.txt
odoo_addon_base_user_role_company-18.0.1.0.2.dist-info/RECORD
