Metadata-Version: 2.1
Name: odoo-addon-base_user_role_company
Version: 18.0.1.0.2
Requires-Python: >=3.10
Requires-Dist: odoo-addon-base_user_role==18.0.*
Requires-Dist: odoo==18.0.*
Summary: User roles by company
Home-page: https://github.com/OCA/server-backend
License: AGPL-3
Author: Open Source Integrators, Odoo Community Association (OCA)
Author-email: support@odoo-community.org
Classifier: Programming Language :: Python
Classifier: Framework :: Odoo
Classifier: Framework :: Odoo :: 18.0
Classifier: License :: OSI Approved :: GNU Affero General Public License v3
Classifier: Development Status :: 4 - Beta
